{
"meta":{"test_sets":[],"test_metrics":[],"learn_metrics":[{"best_value":"Min","name":"Logloss"}],"launch_mode":"Train","parameters":"","iteration_count":500,"learn_sets":["learn"],"name":"experiment"},
"iterations":[
{"learn":[0.6674494141],"iteration":0,"passed_time":0.002684384857,"remaining_time":1.339508044},
{"learn":[0.6504523147],"iteration":1,"passed_time":0.005278267269,"remaining_time":1.31428855},
{"learn":[0.6333148055],"iteration":2,"passed_time":0.007815191337,"remaining_time":1.294716698},
{"learn":[0.6211622582],"iteration":3,"passed_time":0.01116449935,"remaining_time":1.384397919},
{"learn":[0.6074475749],"iteration":4,"passed_time":0.01389899407,"remaining_time":1.376000413},
{"learn":[0.5966578002],"iteration":5,"passed_time":0.01645212156,"remaining_time":1.354558008},
{"learn":[0.5778417884],"iteration":6,"passed_time":0.01895963548,"remaining_time":1.335300042},
{"learn":[0.5670910766],"iteration":7,"passed_time":0.02137951718,"remaining_time":1.314840307},
{"learn":[0.5559492952],"iteration":8,"passed_time":0.02430922289,"remaining_time":1.32620316},
{"learn":[0.5449595315],"iteration":9,"passed_time":0.02738124108,"remaining_time":1.341680813},
{"learn":[0.5320206942],"iteration":10,"passed_time":0.03016361284,"remaining_time":1.340909698},
{"learn":[0.5238365831],"iteration":11,"passed_time":0.03272908698,"remaining_time":1.33098287},
{"learn":[0.5153412035],"iteration":12,"passed_time":0.03515646239,"remaining_time":1.317015168},
{"learn":[0.5092053401],"iteration":13,"passed_time":0.03770661776,"remaining_time":1.308958302},
{"learn":[0.5025161318],"iteration":14,"passed_time":0.04034412817,"remaining_time":1.304460144},
{"learn":[0.4959848498],"iteration":15,"passed_time":0.04288123394,"remaining_time":1.297157327},
{"learn":[0.490506361],"iteration":16,"passed_time":0.04536742002,"remaining_time":1.288968463},
{"learn":[0.480807658],"iteration":17,"passed_time":0.04787610861,"remaining_time":1.282015797},
{"learn":[0.4756722872],"iteration":18,"passed_time":0.05028566165,"remaining_time":1.273021224},
{"learn":[0.4700968172],"iteration":19,"passed_time":0.05286030724,"remaining_time":1.268647374},
{"learn":[0.4646690207],"iteration":20,"passed_time":0.05544815243,"remaining_time":1.264745953},
{"learn":[0.4603218953],"iteration":21,"passed_time":0.05800699649,"remaining_time":1.260333833},
{"learn":[0.4546964266],"iteration":22,"passed_time":0.06051942107,"remaining_time":1.255120167},
{"learn":[0.4504894413],"iteration":23,"passed_time":0.06298880375,"remaining_time":1.249277941},
{"learn":[0.4446285417],"iteration":24,"passed_time":0.06550307423,"remaining_time":1.24455841},
{"learn":[0.4423962311],"iteration":25,"passed_time":0.06806566604,"remaining_time":1.24088945},
{"learn":[0.4394518624],"iteration":26,"passed_time":0.07058548315,"remaining_time":1.236553094},
{"learn":[0.4353078969],"iteration":27,"passed_time":0.07315907379,"remaining_time":1.233252958},
{"learn":[0.4314286432],"iteration":28,"passed_time":0.07560352053,"remaining_time":1.227905454},
{"learn":[0.4278322559],"iteration":29,"passed_time":0.07820558998,"remaining_time":1.22522091},
{"learn":[0.4246419628],"iteration":30,"passed_time":0.08073869042,"remaining_time":1.221498252},
{"learn":[0.4223866323],"iteration":31,"passed_time":0.08331562656,"remaining_time":1.218491038},
{"learn":[0.4196621389],"iteration":32,"passed_time":0.08584676386,"remaining_time":1.21486178},
{"learn":[0.4172972465],"iteration":33,"passed_time":0.08843674747,"remaining_time":1.212103656},
{"learn":[0.4132746369],"iteration":34,"passed_time":0.0910248531,"remaining_time":1.209330191},
{"learn":[0.4110883525],"iteration":35,"passed_time":0.09357471881,"remaining_time":1.206074154},
{"learn":[0.4083470274],"iteration":36,"passed_time":0.09611726111,"remaining_time":1.202764646},
{"learn":[0.4057480427],"iteration":37,"passed_time":0.09833173143,"remaining_time":1.19550684},
{"learn":[0.4030972801],"iteration":38,"passed_time":0.100978932,"remaining_time":1.193622761},
{"learn":[0.4013998158],"iteration":39,"passed_time":0.1035510591,"remaining_time":1.190837179},
{"learn":[0.3996094186],"iteration":40,"passed_time":0.1060262043,"remaining_time":1.186976287},
{"learn":[0.3981139568],"iteration":41,"passed_time":0.108597282,"remaining_time":1.184227504},
{"learn":[0.3961245657],"iteration":42,"passed_time":0.111196487,"remaining_time":1.18178592},
{"learn":[0.3944563181],"iteration":43,"passed_time":0.113799046,"remaining_time":1.179371931},
{"learn":[0.3921461766],"iteration":44,"passed_time":0.1166751328,"remaining_time":1.179715231},
{"learn":[0.3904632368],"iteration":45,"passed_time":0.1193926634,"remaining_time":1.178353678},
{"learn":[0.3883904183],"iteration":46,"passed_time":0.1218851603,"remaining_time":1.174765481},
{"learn":[0.386832112],"iteration":47,"passed_time":0.1244358565,"remaining_time":1.171770982},
{"learn":[0.3843863973],"iteration":48,"passed_time":0.1268863302,"remaining_time":1.167872141},
{"learn":[0.3828024514],"iteration":49,"passed_time":0.1298625362,"remaining_time":1.168762826},
{"learn":[0.3815739055],"iteration":50,"passed_time":0.1339255465,"remaining_time":1.179070008},
{"learn":[0.3800227002],"iteration":51,"passed_time":0.1367253737,"remaining_time":1.177941681},
{"learn":[0.3776592842],"iteration":52,"passed_time":0.1392131459,"remaining_time":1.17411842},
{"learn":[0.3759559515],"iteration":53,"passed_time":0.1416318501,"remaining_time":1.16977417},
{"learn":[0.3747563484],"iteration":54,"passed_time":0.1441122331,"remaining_time":1.165998977},
{"learn":[0.373231766],"iteration":55,"passed_time":0.1468406688,"remaining_time":1.164236731},
{"learn":[0.3716538784],"iteration":56,"passed_time":0.1494626428,"remaining_time":1.161613171},
{"learn":[0.3705785936],"iteration":57,"passed_time":0.1520591431,"remaining_time":1.158795539},
{"learn":[0.3691496197],"iteration":58,"passed_time":0.15461741,"remaining_time":1.155699624},
{"learn":[0.3681349814],"iteration":59,"passed_time":0.1571390018,"remaining_time":1.15235268},
{"learn":[0.3674751266],"iteration":60,"passed_time":0.1597239176,"remaining_time":1.149488522},
{"learn":[0.3654688652],"iteration":61,"passed_time":0.162171396,"remaining_time":1.145662442},
{"learn":[0.3642702886],"iteration":62,"passed_time":0.1646955975,"remaining_time":1.142412319},
{"learn":[0.3633617313],"iteration":63,"passed_time":0.1671169396,"remaining_time":1.138484151},
{"learn":[0.3627526852],"iteration":64,"passed_time":0.16952272,"remaining_time":1.134498203},
{"learn":[0.3618521699],"iteration":65,"passed_time":0.1719946116,"remaining_time":1.13099487},
{"learn":[0.3598861267],"iteration":66,"passed_time":0.1745242896,"remaining_time":1.127895782},
{"learn":[0.3588546047],"iteration":67,"passed_time":0.1770552936,"remaining_time":1.124821865},
{"learn":[0.3581041488],"iteration":68,"passed_time":0.1795157542,"remaining_time":1.121323045},
{"learn":[0.3576321487],"iteration":69,"passed_time":0.1820079458,"remaining_time":1.11804881},
{"learn":[0.3565879033],"iteration":70,"passed_time":0.1844936926,"remaining_time":1.114757664},
{"learn":[0.3556310817],"iteration":71,"passed_time":0.1869185591,"remaining_time":1.11112699},
{"learn":[0.3548578077],"iteration":72,"passed_time":0.1893690477,"remaining_time":1.107679224},
{"learn":[0.3542579715],"iteration":73,"passed_time":0.1918600614,"remaining_time":1.104491705},
{"learn":[0.3536268617],"iteration":74,"passed_time":0.1943606741,"remaining_time":1.101377153},
{"learn":[0.3525176494],"iteration":75,"passed_time":0.1968512435,"remaining_time":1.098222727},
{"learn":[0.3517575702],"iteration":76,"passed_time":0.1993090335,"remaining_time":1.09490547},
{"learn":[0.3510024638],"iteration":77,"passed_time":0.2018209308,"remaining_time":1.091902984},
{"learn":[0.3502954135],"iteration":78,"passed_time":0.204343192,"remaining_time":1.08896815},
{"learn":[0.3496619296],"iteration":79,"passed_time":0.2068303457,"remaining_time":1.085859315},
{"learn":[0.3488121535],"iteration":80,"passed_time":0.2093165892,"remaining_time":1.082761122},
{"learn":[0.3476192205],"iteration":81,"passed_time":0.2117945964,"remaining_time":1.079635869},
{"learn":[0.3471396752],"iteration":82,"passed_time":0.2142876691,"remaining_time":1.076601904},
{"learn":[0.3464587041],"iteration":83,"passed_time":0.2167500408,"remaining_time":1.073428773},
{"learn":[0.3459197494],"iteration":84,"passed_time":0.2192894517,"remaining_time":1.0706485},
{"learn":[0.3454117833],"iteration":85,"passed_time":0.221978832,"remaining_time":1.068595773},
{"learn":[0.3447206634],"iteration":86,"passed_time":0.2249360475,"remaining_time":1.067799857},
{"learn":[0.343850738],"iteration":87,"passed_time":0.2275650527,"remaining_time":1.065418201},
{"learn":[0.3434029068],"iteration":88,"passed_time":0.230087807,"remaining_time":1.062540322},
{"learn":[0.343136624],"iteration":89,"passed_time":0.2325354745,"remaining_time":1.059328273},
{"learn":[0.3424966787],"iteration":90,"passed_time":0.2353095477,"remaining_time":1.057600055},
{"learn":[0.3419918155],"iteration":91,"passed_time":0.2383624652,"remaining_time":1.057085715},
{"learn":[0.3414142596],"iteration":92,"passed_time":0.2409318413,"remaining_time":1.054400639},
{"learn":[0.3409115442],"iteration":93,"passed_time":0.2434431974,"remaining_time":1.051467427},
{"learn":[0.3404237099],"iteration":94,"passed_time":0.2460096898,"remaining_time":1.048778151},
{"learn":[0.3399603658],"iteration":95,"passed_time":0.248536872,"remaining_time":1.045926003},
{"learn":[0.3392571057],"iteration":96,"passed_time":0.2512946139,"remaining_time":1.044038447},
{"learn":[0.338754424],"iteration":97,"passed_time":0.2538436352,"remaining_time":1.041276953},
{"learn":[0.3382444394],"iteration":98,"passed_time":0.2564483105,"remaining_time":1.038745177},
{"learn":[0.3378814248],"iteration":99,"passed_time":0.2589833178,"remaining_time":1.035933271},
{"learn":[0.3372507361],"iteration":100,"passed_time":0.2614568911,"remaining_time":1.032884154},
{"learn":[0.3367290202],"iteration":101,"passed_time":0.2641720581,"remaining_time":1.030789011},
{"learn":[0.3362642844],"iteration":102,"passed_time":0.2672836993,"remaining_time":1.030209987},
{"learn":[0.3358707948],"iteration":103,"passed_time":0.2698171504,"remaining_time":1.027380688},
{"learn":[0.3353990866],"iteration":104,"passed_time":0.2722996724,"remaining_time":1.024365434},
{"learn":[0.334299913],"iteration":105,"passed_time":0.2748880958,"remaining_time":1.021753866},
{"learn":[0.3338382795],"iteration":106,"passed_time":0.2775440692,"remaining_time":1.019390834},
{"learn":[0.3330974763],"iteration":107,"passed_time":0.2800340112,"remaining_time":1.016419745},
{"learn":[0.3326845836],"iteration":108,"passed_time":0.2832650566,"remaining_time":1.016115937},
{"learn":[0.3323989589],"iteration":109,"passed_time":0.2861922869,"remaining_time":1.014681744},
{"learn":[0.3318114584],"iteration":110,"passed_time":0.289094713,"remaining_time":1.013133724},
{"learn":[0.3315486167],"iteration":111,"passed_time":0.2921952645,"remaining_time":1.012247881},
{"learn":[0.330972205],"iteration":112,"passed_time":0.2950501539,"remaining_time":1.0104815},
{"learn":[0.3303980419],"iteration":113,"passed_time":0.2978892321,"remaining_time":1.008642488},
{"learn":[0.3299417123],"iteration":114,"passed_time":0.3004523024,"remaining_time":1.005862056},
{"learn":[0.329519047],"iteration":115,"passed_time":0.3029955181,"remaining_time":1.003019646},
{"learn":[0.3291420087],"iteration":116,"passed_time":0.3056237106,"remaining_time":1.000460523},
{"learn":[0.3286480103],"iteration":117,"passed_time":0.3081439029,"remaining_time":0.9975506008},
{"learn":[0.328358387],"iteration":118,"passed_time":0.3108245336,"remaining_time":0.9951609015},
{"learn":[0.3275782496],"iteration":119,"passed_time":0.3133849538,"remaining_time":0.9923856871},
{"learn":[0.3271032549],"iteration":120,"passed_time":0.3160238758,"remaining_time":0.9898599085},
{"learn":[0.3267444501],"iteration":121,"passed_time":0.3185109462,"remaining_time":0.9868617841},
{"learn":[0.3261315738],"iteration":122,"passed_time":0.3209969327,"remaining_time":0.9838686475},
{"learn":[0.3257015063],"iteration":123,"passed_time":0.3236406396,"remaining_time":0.9813619395},
{"learn":[0.3252291795],"iteration":124,"passed_time":0.3273595032,"remaining_time":0.9820785095},
{"learn":[0.324866903],"iteration":125,"passed_time":0.330038542,"remaining_time":0.9796382119},
{"learn":[0.3245175941],"iteration":126,"passed_time":0.3324888421,"remaining_time":0.9765223473},
{"learn":[0.3242073517],"iteration":127,"passed_time":0.3349393984,"remaining_time":0.9734176266},
{"learn":[0.3239338895],"iteration":128,"passed_time":0.3374736179,"remaining_time":0.9705636608},
{"learn":[0.3235490276],"iteration":129,"passed_time":0.3406698686,"remaining_time":0.9695988569},
{"learn":[0.3232665435],"iteration":130,"passed_time":0.3435275306,"remaining_time":0.9676462503},
{"learn":[0.3228881519],"iteration":131,"passed_time":0.346072062,"remaining_time":0.9648069608},
{"learn":[0.322567942],"iteration":132,"passed_time":0.3486333021,"remaining_time":0.9620182095},
{"learn":[0.3221037788],"iteration":133,"passed_time":0.3512198294,"remaining_time":0.9593019221},
{"learn":[0.3217450996],"iteration":134,"passed_time":0.3538632498,"remaining_time":0.9567413792},
{"learn":[0.3214278639],"iteration":135,"passed_time":0.356410603,"remaining_time":0.9539224963},
{"learn":[0.321077167],"iteration":136,"passed_time":0.3589312742,"remaining_time":0.9510368797},
{"learn":[0.3207992218],"iteration":137,"passed_time":0.361417627,"remaining_time":0.9480665287},
{"learn":[0.3205849036],"iteration":138,"passed_time":0.3639577736,"remaining_time":0.9452428509},
{"learn":[0.3202469451],"iteration":139,"passed_time":0.3667096938,"remaining_time":0.9429677841},
{"learn":[0.3199345631],"iteration":140,"passed_time":0.369093003,"remaining_time":0.9397474332},
{"learn":[0.3196588815],"iteration":141,"passed_time":0.3718968376,"remaining_time":0.9375990695},
{"learn":[0.319314138],"iteration":142,"passed_time":0.3743640231,"remaining_time":0.9346010927},
{"learn":[0.3191244423],"iteration":143,"passed_time":0.3768695821,"remaining_time":0.9317053558},
{"learn":[0.3188275166],"iteration":144,"passed_time":0.3793195812,"remaining_time":0.9286789746},
{"learn":[0.3184464071],"iteration":145,"passed_time":0.3817784125,"remaining_time":0.9256819043},
{"learn":[0.31809683],"iteration":146,"passed_time":0.3841388668,"remaining_time":0.9224559183},
{"learn":[0.3177967641],"iteration":147,"passed_time":0.3880952518,"remaining_time":0.9230373556},
{"learn":[0.3175906171],"iteration":148,"passed_time":0.3912470732,"remaining_time":0.9216625685},
{"learn":[0.3172255603],"iteration":149,"passed_time":0.3939161343,"remaining_time":0.9191376468},
{"learn":[0.3169246289],"iteration":150,"passed_time":0.3966544406,"remaining_time":0.9167708593},
{"learn":[0.3166935663],"iteration":151,"passed_time":0.3993225436,"remaining_time":0.9142384551},
{"learn":[0.3163712649],"iteration":152,"passed_time":0.4019746713,"remaining_time":0.9116680453},
{"learn":[0.3160942253],"iteration":153,"passed_time":0.4049161785,"remaining_time":0.9097467388},
{"learn":[0.3159260812],"iteration":154,"passed_time":0.4078836948,"remaining_time":0.9078701594},
{"learn":[0.3157360861],"iteration":155,"passed_time":0.4105485169,"remaining_time":0.9053121141},
{"learn":[0.3155275298],"iteration":156,"passed_time":0.4132088975,"remaining_time":0.9027430053},
{"learn":[0.3150789403],"iteration":157,"passed_time":0.4159507926,"remaining_time":0.9003491839},
{"learn":[0.3148147064],"iteration":158,"passed_time":0.4194416057,"remaining_time":0.8995571544},
{"learn":[0.3141952127],"iteration":159,"passed_time":0.4225349646,"remaining_time":0.8978867997},
{"learn":[0.3139258892],"iteration":160,"passed_time":0.4253787603,"remaining_time":0.8956732904},
{"learn":[0.3136802696],"iteration":161,"passed_time":0.4281668615,"remaining_time":0.8933357974},
{"learn":[0.3132849039],"iteration":162,"passed_time":0.4314814579,"remaining_time":0.8920812963},
{"learn":[0.312892328],"iteration":163,"passed_time":0.4339264754,"remaining_time":0.8890200959},
{"learn":[0.3125997608],"iteration":164,"passed_time":0.4363023749,"remaining_time":0.885826034},
{"learn":[0.3122793544],"iteration":165,"passed_time":0.4386583429,"remaining_time":0.8826017261},
{"learn":[0.3120013904],"iteration":166,"passed_time":0.4412863876,"remaining_time":0.8799303417},
{"learn":[0.3117353022],"iteration":167,"passed_time":0.4439243939,"remaining_time":0.8772791594},
{"learn":[0.3115107987],"iteration":168,"passed_time":0.4467791575,"remaining_time":0.8750526695},
{"learn":[0.3112537734],"iteration":169,"passed_time":0.449328357,"remaining_time":0.8722256342},
{"learn":[0.3109034383],"iteration":170,"passed_time":0.4518942134,"remaining_time":0.869433896},
{"learn":[0.3105054853],"iteration":171,"passed_time":0.4543832134,"remaining_time":0.866498221},
{"learn":[0.3103219405],"iteration":172,"passed_time":0.4571095881,"remaining_time":0.864016389},
{"learn":[0.3100993095],"iteration":173,"passed_time":0.459729843,"remaining_time":0.8613329242},
{"learn":[0.3098594804],"iteration":174,"passed_time":0.4622693205,"remaining_time":0.8585001667},
{"learn":[0.3096440374],"iteration":175,"passed_time":0.4647442242,"remaining_time":0.8555518672},
{"learn":[0.3094278862],"iteration":176,"passed_time":0.4672777468,"remaining_time":0.8527158882},
{"learn":[0.3091714716],"iteration":177,"passed_time":0.4697708352,"remaining_time":0.8498101625},
{"learn":[0.3090219772],"iteration":178,"passed_time":0.4722424147,"remaining_time":0.8468704755},
{"learn":[0.3088531498],"iteration":179,"passed_time":0.4748059563,"remaining_time":0.8440994779},
{"learn":[0.3085414419],"iteration":180,"passed_time":0.4773767466,"remaining_time":0.8413435478},
{"learn":[0.3079087173],"iteration":181,"passed_time":0.479899436,"remaining_time":0.838505608},
{"learn":[0.3075652443],"iteration":182,"passed_time":0.4825851103,"remaining_time":0.8359534424},
{"learn":[0.3070954257],"iteration":183,"passed_time":0.4852091457,"remaining_time":0.8332939676},
{"learn":[0.3068120279],"iteration":184,"passed_time":0.4877653444,"remaining_time":0.8305193701},
{"learn":[0.3065616876],"iteration":185,"passed_time":0.4906885254,"remaining_time":0.8283666505},
{"learn":[0.3064802042],"iteration":186,"passed_time":0.4934242764,"remaining_time":0.8258919707},
{"learn":[0.3063341547],"iteration":187,"passed_time":0.496228256,"remaining_time":0.8235277441},
{"learn":[0.3060919613],"iteration":188,"passed_time":0.4990308647,"remaining_time":0.8211566081},
{"learn":[0.3057418044],"iteration":189,"passed_time":0.5016250125,"remaining_time":0.8184408099},
{"learn":[0.3052663767],"iteration":190,"passed_time":0.505902315,"remaining_time":0.8184492949},
{"learn":[0.305005225],"iteration":191,"passed_time":0.511253755,"remaining_time":0.8201362321},
{"learn":[0.3047286063],"iteration":192,"passed_time":0.5166198099,"remaining_time":0.82177348},
{"learn":[0.3045928187],"iteration":193,"passed_time":0.5223557808,"remaining_time":0.8239220047},
{"learn":[0.3044204566],"iteration":194,"passed_time":0.5272104661,"remaining_time":0.8246112418},
{"learn":[0.3042625429],"iteration":195,"passed_time":0.5310143748,"remaining_time":0.8236141324},
{"learn":[0.3040002501],"iteration":196,"passed_time":0.5354517494,"remaining_time":0.823562843},
{"learn":[0.303706925],"iteration":197,"passed_time":0.5388135455,"remaining_time":0.8218267209},
{"learn":[0.3035323349],"iteration":198,"passed_time":0.5422519843,"remaining_time":0.8201901873},
{"learn":[0.3034444007],"iteration":199,"passed_time":0.5453961873,"remaining_time":0.818094281},
{"learn":[0.3031926083],"iteration":200,"passed_time":0.5491255088,"remaining_time":0.816858344},
{"learn":[0.3029666134],"iteration":201,"passed_time":0.5527135685,"remaining_time":0.8153893239},
{"learn":[0.3027956753],"iteration":202,"passed_time":0.5561725549,"remaining_time":0.8137105852},
{"learn":[0.3025256341],"iteration":203,"passed_time":0.5589261966,"remaining_time":0.810990952},
{"learn":[0.3022965806],"iteration":204,"passed_time":0.5619043558,"remaining_time":0.808594073},
{"learn":[0.3020100431],"iteration":205,"passed_time":0.5664469249,"remaining_time":0.8084242521},
{"learn":[0.3016597534],"iteration":206,"passed_time":0.569647771,"remaining_time":0.8063130285},
{"learn":[0.3011562244],"iteration":207,"passed_time":0.5726354312,"remaining_time":0.8038920477},
{"learn":[0.3009233347],"iteration":208,"passed_time":0.5754680543,"remaining_time":0.8012497789},
{"learn":[0.3007466252],"iteration":209,"passed_time":0.5790791969,"remaining_time":0.7996807957},
{"learn":[0.3005505774],"iteration":210,"passed_time":0.5820605067,"remaining_time":0.7972297935},
{"learn":[0.3002761913],"iteration":211,"passed_time":0.5848636808,"remaining_time":0.7945317928},
{"learn":[0.3001155023],"iteration":212,"passed_time":0.5889681743,"remaining_time":0.7935862254},
{"learn":[0.2999721323],"iteration":213,"passed_time":0.5921350266,"remaining_time":0.7913580262},
{"learn":[0.299758027],"iteration":214,"passed_time":0.5950876944,"remaining_time":0.7888371763},
{"learn":[0.299543096],"iteration":215,"passed_time":0.598170669,"remaining_time":0.7864836575},
{"learn":[0.2993670676],"iteration":216,"passed_time":0.6016714753,"remaining_time":0.7846683295},
{"learn":[0.2992218315],"iteration":217,"passed_time":0.6043421877,"remaining_time":0.7817637474},
{"learn":[0.29898554],"iteration":218,"passed_time":0.6071693803,"remaining_time":0.7790620816},
{"learn":[0.2988661427],"iteration":219,"passed_time":0.6098590856,"remaining_time":0.7761842907},
{"learn":[0.2985144638],"iteration":220,"passed_time":0.6124644955,"remaining_time":0.7732017839},
{"learn":[0.2983843753],"iteration":221,"passed_time":0.6150396157,"remaining_time":0.770184744},
{"learn":[0.298166617],"iteration":222,"passed_time":0.6178546864,"remaining_time":0.7674697226},
{"learn":[0.2980153091],"iteration":223,"passed_time":0.6203762803,"remaining_time":0.7643922025},
{"learn":[0.2977682909],"iteration":224,"passed_time":0.6231888204,"remaining_time":0.7616752249},
{"learn":[0.2975432445],"iteration":225,"passed_time":0.6260446062,"remaining_time":0.7590098322},
{"learn":[0.2974000658],"iteration":226,"passed_time":0.6285925839,"remaining_time":0.7559725789},
{"learn":[0.2970196896],"iteration":227,"passed_time":0.6310511708,"remaining_time":0.7528329757},
{"learn":[0.2966000291],"iteration":228,"passed_time":0.6334945006,"remaining_time":0.749681265},
{"learn":[0.2964415466],"iteration":229,"passed_time":0.6359958298,"remaining_time":0.7466038002},
{"learn":[0.2962979168],"iteration":230,"passed_time":0.6388528765,"remaining_time":0.7439455575},
{"learn":[0.2960828225],"iteration":231,"passed_time":0.6413922326,"remaining_time":0.7409186135},
{"learn":[0.2958643701],"iteration":232,"passed_time":0.6437899502,"remaining_time":0.7377335481},
{"learn":[0.2956075555],"iteration":233,"passed_time":0.6462599574,"remaining_time":0.7346373875},
{"learn":[0.295374425],"iteration":234,"passed_time":0.6488205516,"remaining_time":0.7316487071},
{"learn":[0.2950671219],"iteration":235,"passed_time":0.651284647,"remaining_time":0.7285557068},
{"learn":[0.2948162271],"iteration":236,"passed_time":0.6544583254,"remaining_time":0.7262554412},
{"learn":[0.2945396245],"iteration":237,"passed_time":0.6570792415,"remaining_time":0.7233393331},
{"learn":[0.294380065],"iteration":238,"passed_time":0.6596035656,"remaining_time":0.7203202118},
{"learn":[0.2941392335],"iteration":239,"passed_time":0.6620900339,"remaining_time":0.7172642034},
{"learn":[0.2937633095],"iteration":240,"passed_time":0.6646092642,"remaining_time":0.7142481304},
{"learn":[0.2935422932],"iteration":241,"passed_time":0.6671268734,"remaining_time":0.7112344353},
{"learn":[0.2933368671],"iteration":242,"passed_time":0.669698926,"remaining_time":0.7082824032},
{"learn":[0.2931728712],"iteration":243,"passed_time":0.6722442768,"remaining_time":0.7053054708},
{"learn":[0.2930458949],"iteration":244,"passed_time":0.6746929837,"remaining_time":0.7022314728},
{"learn":[0.2929718833],"iteration":245,"passed_time":0.6772104062,"remaining_time":0.6992335088},
{"learn":[0.2928467279],"iteration":246,"passed_time":0.679661364,"remaining_time":0.6961713567},
{"learn":[0.2925397996],"iteration":247,"passed_time":0.682210757,"remaining_time":0.6932141563},
{"learn":[0.2924216013],"iteration":248,"passed_time":0.6846826938,"remaining_time":0.6901821532},
{"learn":[0.2922940543],"iteration":249,"passed_time":0.6872160576,"remaining_time":0.6872160576},
{"learn":[0.2919895404],"iteration":250,"passed_time":0.6897085474,"remaining_time":0.6842128617},
{"learn":[0.2918002645],"iteration":251,"passed_time":0.6921601369,"remaining_time":0.681173468},
{"learn":[0.2914856014],"iteration":252,"passed_time":0.6951190055,"remaining_time":0.6786339698},
{"learn":[0.2911536956],"iteration":253,"passed_time":0.6979760012,"remaining_time":0.6759925051},
{"learn":[0.2908819488],"iteration":254,"passed_time":0.7005948231,"remaining_time":0.6731205163},
{"learn":[0.2906558273],"iteration":255,"passed_time":0.702951179,"remaining_time":0.6700003425},
{"learn":[0.2903247081],"iteration":256,"passed_time":0.7061977395,"remaining_time":0.6677278237},
{"learn":[0.2899091326],"iteration":257,"passed_time":0.7091572312,"remaining_time":0.6651784882},
{"learn":[0.2895992632],"iteration":258,"passed_time":0.711740594,"remaining_time":0.6622759967},
{"learn":[0.2893376574],"iteration":259,"passed_time":0.7142715952,"remaining_time":0.6593276264},
{"learn":[0.2890247716],"iteration":260,"passed_time":0.7168491256,"remaining_time":0.6564250614},
{"learn":[0.2887911496],"iteration":261,"passed_time":0.7193787224,"remaining_time":0.6534814348},
{"learn":[0.2884851117],"iteration":262,"passed_time":0.7218361126,"remaining_time":0.6504758885},
{"learn":[0.2882929793],"iteration":263,"passed_time":0.724375826,"remaining_time":0.6475480868},
{"learn":[0.2880205982],"iteration":264,"passed_time":0.7269068813,"remaining_time":0.6446155363},
{"learn":[0.2878305208],"iteration":265,"passed_time":0.729944951,"remaining_time":0.6421320246},
{"learn":[0.2875095261],"iteration":266,"passed_time":0.7325629873,"remaining_time":0.6392778129},
{"learn":[0.2872513392],"iteration":267,"passed_time":0.7351142593,"remaining_time":0.6363675678},
{"learn":[0.287048022],"iteration":268,"passed_time":0.7376522006,"remaining_time":0.633448544},
{"learn":[0.2868480878],"iteration":269,"passed_time":0.7402503014,"remaining_time":0.6305835901},
{"learn":[0.2865993116],"iteration":270,"passed_time":0.7429125553,"remaining_time":0.6277748161},
{"learn":[0.2863361954],"iteration":271,"passed_time":0.7454540943,"remaining_time":0.624865932},
{"learn":[0.2860529883],"iteration":272,"passed_time":0.7479528996,"remaining_time":0.6219242059},
{"learn":[0.2857811129],"iteration":273,"passed_time":0.7504615754,"remaining_time":0.6189938541},
{"learn":[0.2855070323],"iteration":274,"passed_time":0.7529915633,"remaining_time":0.6160840064},
{"learn":[0.2852510186],"iteration":275,"passed_time":0.755623287,"remaining_time":0.6132594793},
{"learn":[0.2849150928],"iteration":276,"passed_time":0.7587137852,"remaining_time":0.6108056827},
{"learn":[0.2846579745],"iteration":277,"passed_time":0.7613237328,"remaining_time":0.6079635564},
{"learn":[0.2845116124],"iteration":278,"passed_time":0.7638949136,"remaining_time":0.6050923867},
{"learn":[0.2842272017],"iteration":279,"passed_time":0.7664176166,"remaining_time":0.6021852702},
{"learn":[0.2838463036],"iteration":280,"passed_time":0.7689714132,"remaining_time":0.5993051227},
{"learn":[0.2835994858],"iteration":281,"passed_time":0.7716636117,"remaining_time":0.5965342814},
{"learn":[0.283224103],"iteration":282,"passed_time":0.7742194355,"remaining_time":0.5936594258},
{"learn":[0.2830540637],"iteration":283,"passed_time":0.7768366905,"remaining_time":0.5908335392},
{"learn":[0.282859675],"iteration":284,"passed_time":0.7792952642,"remaining_time":0.5878894099},
{"learn":[0.2826126342],"iteration":285,"passed_time":0.7819853083,"remaining_time":0.585121874},
{"learn":[0.2824462312],"iteration":286,"passed_time":0.7844895872,"remaining_time":0.5822170107},
{"learn":[0.2821600439],"iteration":287,"passed_time":0.7871430862,"remaining_time":0.5794247718},
{"learn":[0.2819287243],"iteration":288,"passed_time":0.7896431456,"remaining_time":0.5765214661},
{"learn":[0.2816357134],"iteration":289,"passed_time":0.7921701158,"remaining_time":0.5736404287},
{"learn":[0.2814920625],"iteration":290,"passed_time":0.7947325327,"remaining_time":0.5707872829},
{"learn":[0.2812014138],"iteration":291,"passed_time":0.7972333207,"remaining_time":0.5678922284},
{"learn":[0.2809809011],"iteration":292,"passed_time":0.7997206939,"remaining_time":0.5649903878},
{"learn":[0.2807929231],"iteration":293,"passed_time":0.8026170824,"remaining_time":0.5623779557},
{"learn":[0.2804995746],"iteration":294,"passed_time":0.8054308068,"remaining_time":0.5597061539},
{"learn":[0.2801817101],"iteration":295,"passed_time":0.8080706106,"remaining_time":0.5569135289},
{"learn":[0.2800258007],"iteration":296,"passed_time":0.8118488171,"remaining_time":0.5549000332},
{"learn":[0.2798441344],"iteration":297,"passed_time":0.8145034629,"remaining_time":0.5521130856},
{"learn":[0.279716489],"iteration":298,"passed_time":0.8179411268,"remaining_time":0.5498533996},
{"learn":[0.2794777869],"iteration":299,"passed_time":0.8208358297,"remaining_time":0.5472238865},
{"learn":[0.2792527246],"iteration":300,"passed_time":0.8232674182,"remaining_time":0.5442864326},
{"learn":[0.2790544247],"iteration":301,"passed_time":0.8260833982,"remaining_time":0.5416043472},
{"learn":[0.2788298124],"iteration":302,"passed_time":0.8285790454,"remaining_time":0.5387131087},
{"learn":[0.2786179564],"iteration":303,"passed_time":0.8310549648,"remaining_time":0.5358117536},
{"learn":[0.2784615051],"iteration":304,"passed_time":0.8341043479,"remaining_time":0.533279829},
{"learn":[0.2781154697],"iteration":305,"passed_time":0.8371752346,"remaining_time":0.5307581553},
{"learn":[0.2778648192],"iteration":306,"passed_time":0.8398344982,"remaining_time":0.5279741308},
{"learn":[0.2776320255],"iteration":307,"passed_time":0.8426765657,"remaining_time":0.5253048721},
{"learn":[0.2774179165],"iteration":308,"passed_time":0.8454375397,"remaining_time":0.5225843692},
{"learn":[0.277084082],"iteration":309,"passed_time":0.8480765629,"remaining_time":0.5197888611},
{"learn":[0.2768719343],"iteration":310,"passed_time":0.851024397,"remaining_time":0.5171820291},
{"learn":[0.2765611416],"iteration":311,"passed_time":0.8540259235,"remaining_time":0.5146053641},
{"learn":[0.2764067615],"iteration":312,"passed_time":0.8569085719,"remaining_time":0.5119549615},
{"learn":[0.2760922849],"iteration":313,"passed_time":0.8597257081,"remaining_time":0.5092642729},
{"learn":[0.2758748632],"iteration":314,"passed_time":0.8635937101,"remaining_time":0.5071899567},
{"learn":[0.2757334449],"iteration":315,"passed_time":0.866300134,"remaining_time":0.5044279261},
{"learn":[0.2755319534],"iteration":316,"passed_time":0.8688225348,"remaining_time":0.5015600122},
{"learn":[0.2752449182],"iteration":317,"passed_time":0.8713929617,"remaining_time":0.4987217579},
{"learn":[0.2750394257],"iteration":318,"passed_time":0.873660996,"remaining_time":0.4957136059},
{"learn":[0.2747992208],"iteration":319,"passed_time":0.8763561285,"remaining_time":0.4929503223},
{"learn":[0.2745522177],"iteration":320,"passed_time":0.8788232638,"remaining_time":0.4900603247},
{"learn":[0.2743778829],"iteration":321,"passed_time":0.881373437,"remaining_time":0.4872188565},
{"learn":[0.274146899],"iteration":322,"passed_time":0.8840528224,"remaining_time":0.4844499987},
{"learn":[0.273926676],"iteration":323,"passed_time":0.886530752,"remaining_time":0.4815722603},
{"learn":[0.2737140154],"iteration":324,"passed_time":0.8890334942,"remaining_time":0.478710343},
{"learn":[0.2735653725],"iteration":325,"passed_time":0.8917216087,"remaining_time":0.4759495703},
{"learn":[0.2732549414],"iteration":326,"passed_time":0.8941886815,"remaining_time":0.4730722994},
{"learn":[0.2730524014],"iteration":327,"passed_time":0.8967093327,"remaining_time":0.4702256257},
{"learn":[0.272944778],"iteration":328,"passed_time":0.8991654624,"remaining_time":0.4673473984},
{"learn":[0.2727246611],"iteration":329,"passed_time":0.9020315878,"remaining_time":0.4646829392},
{"learn":[0.2726155568],"iteration":330,"passed_time":0.9045235236,"remaining_time":0.4618262099},
{"learn":[0.2724358648],"iteration":331,"passed_time":0.9070063047,"remaining_time":0.4589670457},
{"learn":[0.2721323862],"iteration":332,"passed_time":0.9095559125,"remaining_time":0.4561436558},
{"learn":[0.2718322847],"iteration":333,"passed_time":0.9121104825,"remaining_time":0.4533243716},
{"learn":[0.2716796987],"iteration":334,"passed_time":0.9147564882,"remaining_time":0.4505517031},
{"learn":[0.2713225005],"iteration":335,"passed_time":0.9173611642,"remaining_time":0.4477596159},
{"learn":[0.2710965017],"iteration":336,"passed_time":0.9198827342,"remaining_time":0.4449284441},
{"learn":[0.2708645194],"iteration":337,"passed_time":0.922514087,"remaining_time":0.4421517222},
{"learn":[0.2706616309],"iteration":338,"passed_time":0.9251547309,"remaining_time":0.4393802704},
{"learn":[0.270608887],"iteration":339,"passed_time":0.9276506403,"remaining_time":0.4365414778},
{"learn":[0.2703752364],"iteration":340,"passed_time":0.9301567327,"remaining_time":0.4337094443},
{"learn":[0.2701070456],"iteration":341,"passed_time":0.9327548588,"remaining_time":0.4309218353},
{"learn":[0.2699592063],"iteration":342,"passed_time":0.9353325167,"remaining_time":0.4281259625},
{"learn":[0.2698292148],"iteration":343,"passed_time":0.9382069276,"remaining_time":0.4254659323},
{"learn":[0.2697107295],"iteration":344,"passed_time":0.9408027097,"remaining_time":0.4226794783},
{"learn":[0.2695952525],"iteration":345,"passed_time":0.9432761308,"remaining_time":0.4198396652},
{"learn":[0.2694902943],"iteration":346,"passed_time":0.9456825628,"remaining_time":0.4169724268},
{"learn":[0.2693106795],"iteration":347,"passed_time":0.9481498923,"remaining_time":0.4141344357},
{"learn":[0.269121007],"iteration":348,"passed_time":0.9506960907,"remaining_time":0.4113326926},
{"learn":[0.269040434],"iteration":349,"passed_time":0.9533065906,"remaining_time":0.4085599674},
{"learn":[0.2688260767],"iteration":350,"passed_time":0.9558866745,"remaining_time":0.405775255},
{"learn":[0.268597369],"iteration":351,"passed_time":0.9583924262,"remaining_time":0.4029604519},
{"learn":[0.2684572072],"iteration":352,"passed_time":0.9608360453,"remaining_time":0.400121526},
{"learn":[0.268254278],"iteration":353,"passed_time":0.9632181221,"remaining_time":0.3972594515},
{"learn":[0.2680374316],"iteration":354,"passed_time":0.9658017696,"remaining_time":0.3944824129},
{"learn":[0.267862349],"iteration":355,"passed_time":0.9685086299,"remaining_time":0.3917562997},
{"learn":[0.2676912207],"iteration":356,"passed_time":0.9710962902,"remaining_time":0.3889825476},
{"learn":[0.2674251749],"iteration":357,"passed_time":0.9736382371,"remaining_time":0.386191703},
{"learn":[0.2672372412],"iteration":358,"passed_time":0.9760151799,"remaining_time":0.3833374383},
{"learn":[0.2669663324],"iteration":359,"passed_time":0.978506096,"remaining_time":0.3805301484},
{"learn":[0.2668231483],"iteration":360,"passed_time":0.9810008756,"remaining_time":0.3777260989},
{"learn":[0.2667311971],"iteration":361,"passed_time":0.9838483172,"remaining_time":0.3750581983},
{"learn":[0.2665110464],"iteration":362,"passed_time":0.9864027434,"remaining_time":0.3722787213},
{"learn":[0.2664029149],"iteration":363,"passed_time":0.9887943974,"remaining_time":0.369439665},
{"learn":[0.2661683438],"iteration":364,"passed_time":0.991301678,"remaining_time":0.3666458261},
{"learn":[0.2660148002],"iteration":365,"passed_time":0.9938256732,"remaining_time":0.3638596727},
{"learn":[0.2658184145],"iteration":366,"passed_time":0.9967524503,"remaining_time":0.3612209152},
{"learn":[0.2656348266],"iteration":367,"passed_time":0.9993505718,"remaining_time":0.3584627051},
{"learn":[0.265494551],"iteration":368,"passed_time":1.001929824,"remaining_time":0.355698664},
{"learn":[0.265242681],"iteration":369,"passed_time":1.004466474,"remaining_time":0.352920653},
{"learn":[0.2651571959],"iteration":370,"passed_time":1.006916304,"remaining_time":0.3501137553},
{"learn":[0.2650065411],"iteration":371,"passed_time":1.00950352,"remaining_time":0.3473560499},
{"learn":[0.26485271],"iteration":372,"passed_time":1.012028581,"remaining_time":0.344578096},
{"learn":[0.2646273299],"iteration":373,"passed_time":1.014613266,"remaining_time":0.3418215817},
{"learn":[0.2645070617],"iteration":374,"passed_time":1.017122182,"remaining_time":0.3390407275},
{"learn":[0.2642920703],"iteration":375,"passed_time":1.019608032,"remaining_time":0.3362537127},
{"learn":[0.2640400891],"iteration":376,"passed_time":1.022168222,"remaining_time":0.33349255},
{"learn":[0.2638039878],"iteration":377,"passed_time":1.024701027,"remaining_time":0.330723612},
{"learn":[0.2635969308],"iteration":378,"passed_time":1.027351198,"remaining_time":0.3279933905},
{"learn":[0.2634206154],"iteration":379,"passed_time":1.030008868,"remaining_time":0.3252659584},
{"learn":[0.263169275],"iteration":380,"passed_time":1.032625103,"remaining_time":0.3225259507},
{"learn":[0.2629704291],"iteration":381,"passed_time":1.035133577,"remaining_time":0.319753304},
{"learn":[0.2627670751],"iteration":382,"passed_time":1.03761729,"remaining_time":0.3169744724},
{"learn":[0.2626024515],"iteration":383,"passed_time":1.040134551,"remaining_time":0.3142073124},
{"learn":[0.2624312455],"iteration":384,"passed_time":1.042870682,"remaining_time":0.311506827},
{"learn":[0.2623040635],"iteration":385,"passed_time":1.045657789,"remaining_time":0.3088212122},
{"learn":[0.2622158972],"iteration":386,"passed_time":1.048113882,"remaining_time":0.3060384205},
{"learn":[0.2620232725],"iteration":387,"passed_time":1.050467525,"remaining_time":0.3032277391},
{"learn":[0.2618278548],"iteration":388,"passed_time":1.052985462,"remaining_time":0.3004662885},
{"learn":[0.2617537782],"iteration":389,"passed_time":1.055715681,"remaining_time":0.2977659612},
{"learn":[0.2615000486],"iteration":390,"passed_time":1.058294792,"remaining_time":0.2950233564},
{"learn":[0.2613027498],"iteration":391,"passed_time":1.060809646,"remaining_time":0.292263882},
{"learn":[0.2611155807],"iteration":392,"passed_time":1.063087204,"remaining_time":0.2894410454},
{"learn":[0.260825326],"iteration":393,"passed_time":1.065604895,"remaining_time":0.2866855809},
{"learn":[0.2605306954],"iteration":394,"passed_time":1.068091318,"remaining_time":0.2839230086},
{"learn":[0.2603574545],"iteration":395,"passed_time":1.070703622,"remaining_time":0.2811948905},
{"learn":[0.2602228365],"iteration":396,"passed_time":1.073505896,"remaining_time":0.2785166431},
{"learn":[0.2600032377],"iteration":397,"passed_time":1.076189697,"remaining_time":0.2758074099},
{"learn":[0.2598845549],"iteration":398,"passed_time":1.078704461,"remaining_time":0.2730555153},
{"learn":[0.2596442665],"iteration":399,"passed_time":1.081181414,"remaining_time":0.2702953536},
{"learn":[0.2593555216],"iteration":400,"passed_time":1.083747601,"remaining_time":0.2675586346},
{"learn":[0.259059569],"iteration":401,"passed_time":1.086522387,"remaining_time":0.2648736168},
{"learn":[0.258875361],"iteration":402,"passed_time":1.089044935,"remaining_time":0.2621274409},
{"learn":[0.2587905716],"iteration":403,"passed_time":1.091492238,"remaining_time":0.2593644922},
{"learn":[0.2586175939],"iteration":404,"passed_time":1.094062159,"remaining_time":0.2566318646},
{"learn":[0.2584714387],"iteration":405,"passed_time":1.09663462,"remaining_time":0.2539006262},
{"learn":[0.2583588048],"iteration":406,"passed_time":1.09909961,"remaining_time":0.2511456112},
{"learn":[0.2582088685],"iteration":407,"passed_time":1.101630708,"remaining_time":0.2484069244},
{"learn":[0.2579469703],"iteration":408,"passed_time":1.104180847,"remaining_time":0.2456734893},
{"learn":[0.2577642295],"iteration":409,"passed_time":1.106650161,"remaining_time":0.2429232061},
{"learn":[0.2575717453],"iteration":410,"passed_time":1.109112885,"remaining_time":0.2401728633},
{"learn":[0.2574091307],"iteration":411,"passed_time":1.11165971,"remaining_time":0.2374418799},
{"learn":[0.25721368],"iteration":412,"passed_time":1.114124468,"remaining_time":0.2346945005},
{"learn":[0.2570165115],"iteration":413,"passed_time":1.11684296,"remaining_time":0.2320011946},
{"learn":[0.2568239589],"iteration":414,"passed_time":1.119443739,"remaining_time":0.2292836574},
{"learn":[0.2567454581],"iteration":415,"passed_time":1.121889952,"remaining_time":0.2265354711},
{"learn":[0.2565042436],"iteration":416,"passed_time":1.124295246,"remaining_time":0.2237805885},
{"learn":[0.2563928017],"iteration":417,"passed_time":1.126792221,"remaining_time":0.221045364},
{"learn":[0.2562271111],"iteration":418,"passed_time":1.129328495,"remaining_time":0.2183188737},
{"learn":[0.2559815754],"iteration":419,"passed_time":1.131846762,"remaining_time":0.2155898594},
{"learn":[0.2557852633],"iteration":420,"passed_time":1.134325693,"remaining_time":0.2128544649},
{"learn":[0.2556259276],"iteration":421,"passed_time":1.136794333,"remaining_time":0.2101183838},
{"learn":[0.2553305245],"iteration":422,"passed_time":1.139624949,"remaining_time":0.2074494587},
{"learn":[0.2551092923],"iteration":423,"passed_time":1.142117552,"remaining_time":0.2047191839},
{"learn":[0.2548483294],"iteration":424,"passed_time":1.144688443,"remaining_time":0.2020038429},
{"learn":[0.2547298355],"iteration":425,"passed_time":1.147194435,"remaining_time":0.1992779066},
{"learn":[0.2546100169],"iteration":426,"passed_time":1.149884961,"remaining_time":0.1965845483},
{"learn":[0.2543905686],"iteration":427,"passed_time":1.152577029,"remaining_time":0.1938914627},
{"learn":[0.2542310728],"iteration":428,"passed_time":1.155055104,"remaining_time":0.191162966},
{"learn":[0.2540129171],"iteration":429,"passed_time":1.157581425,"remaining_time":0.1884434877},
{"learn":[0.2537374561],"iteration":430,"passed_time":1.160265435,"remaining_time":0.1857501508},
{"learn":[0.2535307584],"iteration":431,"passed_time":1.163034796,"remaining_time":0.1830702919},
{"learn":[0.2533649785],"iteration":432,"passed_time":1.165652495,"remaining_time":0.1803665524},
{"learn":[0.2532040953],"iteration":433,"passed_time":1.168086334,"remaining_time":0.1776352489},
{"learn":[0.2530538488],"iteration":434,"passed_time":1.170623117,"remaining_time":0.1749206956},
{"learn":[0.2528656287],"iteration":435,"passed_time":1.173163365,"remaining_time":0.1722074665},
{"learn":[0.2527198235],"iteration":436,"passed_time":1.175759242,"remaining_time":0.1695030487},
{"learn":[0.2524440622],"iteration":437,"passed_time":1.17852745,"remaining_time":0.1668235203},
{"learn":[0.252180206],"iteration":438,"passed_time":1.181579304,"remaining_time":0.1641830013},
{"learn":[0.251976389],"iteration":439,"passed_time":1.184110626,"remaining_time":0.1614696309},
{"learn":[0.2517621781],"iteration":440,"passed_time":1.186619418,"remaining_time":0.1587540718},
{"learn":[0.2515833717],"iteration":441,"passed_time":1.189066956,"remaining_time":0.1560314105},
{"learn":[0.2514300293],"iteration":442,"passed_time":1.191590076,"remaining_time":0.1533197163},
{"learn":[0.2511731838],"iteration":443,"passed_time":1.194711261,"remaining_time":0.1506843032},
{"learn":[0.2510704689],"iteration":444,"passed_time":1.197601773,"remaining_time":0.1480181966},
{"learn":[0.2508322812],"iteration":445,"passed_time":1.200172627,"remaining_time":0.1453123808},
{"learn":[0.2506633858],"iteration":446,"passed_time":1.202720144,"remaining_time":0.1426044019},
{"learn":[0.2505446792],"iteration":447,"passed_time":1.205160784,"remaining_time":0.1398847339},
{"learn":[0.2503438178],"iteration":448,"passed_time":1.207637462,"remaining_time":0.1371704022},
{"learn":[0.250084639],"iteration":449,"passed_time":1.210656806,"remaining_time":0.1345174228},
{"learn":[0.2499480781],"iteration":450,"passed_time":1.213263491,"remaining_time":0.1318179846},
{"learn":[0.2497985754],"iteration":451,"passed_time":1.215728148,"remaining_time":0.1291038741},
{"learn":[0.2497275683],"iteration":452,"passed_time":1.21829714,"remaining_time":0.1264016901},
{"learn":[0.2495934114],"iteration":453,"passed_time":1.220767462,"remaining_time":0.1236900953},
{"learn":[0.2494646854],"iteration":454,"passed_time":1.223282967,"remaining_time":0.1209840297},
{"learn":[0.2491646114],"iteration":455,"passed_time":1.226109147,"remaining_time":0.1183087773},
{"learn":[0.2490414863],"iteration":456,"passed_time":1.228666159,"remaining_time":0.115607538},
{"learn":[0.248782013],"iteration":457,"passed_time":1.231211224,"remaining_time":0.1129058328},
{"learn":[0.2486155677],"iteration":458,"passed_time":1.233755171,"remaining_time":0.1102047103},
{"learn":[0.2484545583],"iteration":459,"passed_time":1.236396546,"remaining_time":0.1075127432},
{"learn":[0.2483480033],"iteration":460,"passed_time":1.241134119,"remaining_time":0.1049983311},
{"learn":[0.2480788088],"iteration":461,"passed_time":1.244248931,"remaining_time":0.1023408211},
{"learn":[0.2479678151],"iteration":462,"passed_time":1.246936525,"remaining_time":0.09964719531},
{"learn":[0.2477222747],"iteration":463,"passed_time":1.249592835,"remaining_time":0.09695116824},
{"learn":[0.2475595023],"iteration":464,"passed_time":1.252020022,"remaining_time":0.0942380662},
{"learn":[0.2473444507],"iteration":465,"passed_time":1.25553181,"remaining_time":0.09160532519},
{"learn":[0.2470828275],"iteration":466,"passed_time":1.258243547,"remaining_time":0.08891228494},
{"learn":[0.2469065385],"iteration":467,"passed_time":1.261031915,"remaining_time":0.08622440445},
{"learn":[0.2466491556],"iteration":468,"passed_time":1.263901557,"remaining_time":0.08354146755},
{"learn":[0.2464950581],"iteration":469,"passed_time":1.266467828,"remaining_time":0.08083837199},
{"learn":[0.2462138509],"iteration":470,"passed_time":1.269251696,"remaining_time":0.07814925515},
{"learn":[0.2460409758],"iteration":471,"passed_time":1.272029415,"remaining_time":0.07545937206},
{"learn":[0.2458859498],"iteration":472,"passed_time":1.27463988,"remaining_time":0.07275957032},
{"learn":[0.2457448598],"iteration":473,"passed_time":1.277544161,"remaining_time":0.07007626201},
{"learn":[0.24550962],"iteration":474,"passed_time":1.280345897,"remaining_time":0.06738662616},
{"learn":[0.245400032],"iteration":475,"passed_time":1.283582976,"remaining_time":0.06471846938},
{"learn":[0.2452752607],"iteration":476,"passed_time":1.288125807,"remaining_time":0.06211088799},
{"learn":[0.2451059085],"iteration":477,"passed_time":1.290782798,"remaining_time":0.05940841328},
{"learn":[0.2448935338],"iteration":478,"passed_time":1.293468981,"remaining_time":0.05670740837},
{"learn":[0.2446770545],"iteration":479,"passed_time":1.296255884,"remaining_time":0.05401066185},
{"learn":[0.2444762953],"iteration":480,"passed_time":1.298890656,"remaining_time":0.05130753112},
{"learn":[0.2444369341],"iteration":481,"passed_time":1.301187798,"remaining_time":0.04859207544},
{"learn":[0.2443488689],"iteration":482,"passed_time":1.303596259,"remaining_time":0.04588226999},
{"learn":[0.2442082506],"iteration":483,"passed_time":1.30601648,"remaining_time":0.04317409851},
{"learn":[0.2439794889],"iteration":484,"passed_time":1.30845196,"remaining_time":0.04046758638},
{"learn":[0.2438245418],"iteration":485,"passed_time":1.311130999,"remaining_time":0.03776920574},
{"learn":[0.2436707524],"iteration":486,"passed_time":1.313696741,"remaining_time":0.03506788015},
{"learn":[0.2435512095],"iteration":487,"passed_time":1.316179223,"remaining_time":0.03236506285},
{"learn":[0.243402013],"iteration":488,"passed_time":1.31862643,"remaining_time":0.02966235323},
{"learn":[0.2432698981],"iteration":489,"passed_time":1.321083513,"remaining_time":0.02696088803},
{"learn":[0.2431573881],"iteration":490,"passed_time":1.323578596,"remaining_time":0.0242611148},
{"learn":[0.2430482151],"iteration":491,"passed_time":1.326116523,"remaining_time":0.0215628703},
{"learn":[0.2428984958],"iteration":492,"passed_time":1.328725635,"remaining_time":0.01886628691},
{"learn":[0.242697773],"iteration":493,"passed_time":1.331318406,"remaining_time":0.01616985919},
{"learn":[0.2424536935],"iteration":494,"passed_time":1.333754274,"remaining_time":0.01347226539},
{"learn":[0.2423059726],"iteration":495,"passed_time":1.336402505,"remaining_time":0.01077743956},
{"learn":[0.2421221014],"iteration":496,"passed_time":1.338965504,"remaining_time":0.008082286742},
{"learn":[0.2420576335],"iteration":497,"passed_time":1.341510086,"remaining_time":0.005387590707},
{"learn":[0.2418395389],"iteration":498,"passed_time":1.344070591,"remaining_time":0.002693528239},
{"learn":[0.2416992577],"iteration":499,"passed_time":1.346614409,"remaining_time":0}
]}